CHANGES
LICENSE
MANIFEST.in
README.rst
setup.py
examples/c-to-c.py
examples/cdecl.py
examples/explore_ast.py
examples/func_calls.py
examples/func_defs.py
examples/rewrite_ast.py
examples/using_cpp_libc.py
examples/using_gcc_E_libc.py
examples/c_files/funky.c
examples/c_files/hash.c
examples/c_files/memmgr.c
examples/c_files/memmgr.h
examples/c_files/year.c
pycparser/__init__.py
pycparser/_ast_gen.py
pycparser/_build_tables.py
pycparser/_c_ast.cfg
pycparser/ast_transforms.py
pycparser/c_ast.py
pycparser/c_generator.py
pycparser/c_lexer.py
pycparser/c_parser.py
pycparser/lextab.py
pycparser/plyparser.py
pycparser/yacctab.py
pycparser.egg-info/PKG-INFO
pycparser.egg-info/SOURCES.txt
pycparser.egg-info/dependency_links.txt
pycparser.egg-info/top_level.txt
pycparser/ply/__init__.py
pycparser/ply/cpp.py
pycparser/ply/ctokens.py
pycparser/ply/lex.py
pycparser/ply/yacc.py
tests/all_tests.py
tests/test_c_ast.py
tests/test_c_generator.py
tests/test_c_lexer.py
tests/test_c_parser.py
tests/test_general.py
tests/c_files/cppd_with_stdio_h.c
tests/c_files/empty.h
tests/c_files/example_c_file.c
tests/c_files/memmgr.c
tests/c_files/memmgr.h
tests/c_files/memmgr_with_h.c
tests/c_files/simplemain.c
tests/c_files/year.c
tests/c_files/hdir/9/inc.h
utils/cpp.exe
utils/fake_libc_include/_ansi.h
utils/fake_libc_include/_fake_defines.h
utils/fake_libc_include/_fake_typedefs.h
utils/fake_libc_include/_syslist.h
utils/fake_libc_include/alloca.h
utils/fake_libc_include/ar.h
utils/fake_libc_include/argz.h
utils/fake_libc_include/assert.h
utils/fake_libc_include/complex.h
utils/fake_libc_include/ctype.h
utils/fake_libc_include/dirent.h
utils/fake_libc_include/envz.h
utils/fake_libc_include/errno.h
utils/fake_libc_include/fastmath.h
utils/fake_libc_include/fcntl.h
utils/fake_libc_include/fenv.h
utils/fake_libc_include/float.h
utils/fake_libc_include/getopt.h
utils/fake_libc_include/grp.h
utils/fake_libc_include/iconv.h
utils/fake_libc_include/ieeefp.h
utils/fake_libc_include/inttypes.h
utils/fake_libc_include/iso646.h
utils/fake_libc_include/langinfo.h
utils/fake_libc_include/libgen.h
utils/fake_libc_include/limits.h
